wepay/__init__.py
wepay/signer/__init__.py
wepay_signer-2.0.0.dist-info/DESCRIPTION.rst
wepay_signer-2.0.0.dist-info/METADATA
wepay_signer-2.0.0.dist-info/RECORD
wepay_signer-2.0.0.dist-info/WHEEL
wepay_signer-2.0.0.dist-info/metadata.json
wepay_signer-2.0.0.dist-info/top_level.txt
