Metadata-Version: 2.0
Name: wepay-signer
Version: 2.0.0
Summary: A Modern Python 2/3 SDK for signing WePay requests.
Home-page: https://github.com/wepay/signer-python
Author: WePay
Author-email: api@wepay.com
License: Apache License 2.0
Keywords: wepay signer
Platform: UNKNOWN
Classifier: Development Status :: 5 - Production/Stable
Classifier: Intended Audience :: Developers
Classifier: Natural Language :: English
Classifier: License :: OSI Approved :: Apache Software License
Classifier: Programming Language :: Python
Classifier: Programming Language :: Python :: 2.7
Classifier: Programming Language :: Python :: 3
Classifier: Programming Language :: Python :: 3.3
Classifier: Programming Language :: Python :: 3.4
Classifier: Programming Language :: Python :: 3.5
Classifier: Programming Language :: Python :: 3.6
Classifier: Programming Language :: Python :: Implementation :: PyPy
Requires-Dist: autoflake (==0.6.6)
Requires-Dist: autopep8 (==1.2.4)
Requires-Dist: pylint (==1.6.4)
Requires-Dist: six (==1.10.0)
